depth2stereo/__init__.py
depth2stereo-0.1.dist-info/METADATA
depth2stereo-0.1.dist-info/WHEEL
depth2stereo-0.1.dist-info/top_level.txt
depth2stereo-0.1.dist-info/RECORD
