Metadata-Version: 2.1
Name: depth2stereo
Version: 0.1
Summary: Create steroscopic images from image + depthmap
Home-page: https://github.com/jaroslaw-weber/depth2stereo
Author: Jaroslaw Weber
Author-email: jaroslawweber@gmail.com
License: MIT
Platform: UNKNOWN
